[{"title":"Java Book","imageUrl":"https://in.bpbonline.com/cdn/shop/products/1021_Front_200x.jpg?v=1625292682","description":"Java is multiple language","price":"400"},{"title":"Go lang","imageUrl":"https://d2sofvawe08yqg.cloudfront.net/productiongo/s_hero?1620389943","description":"Go lang ","price":"100"},{"title":"Go lang","imageUrl":"https://d2sofvawe08yqg.cloudfront.net/productiongo/s_hero?1620389943","description":"Golang, or simply Go, is an open-source programming language developed by Google. It is designed","price":"450"},{"title":"Go","imageUrl":"https://d2sofvawe08yqg.cloudfront.net/productiongo/s_hero?1620389943","description":"Compiled & Statically Typed: Ensures fast execution and type safety.","price":"25"},{"title":"Go","imageUrl":"https://d2sofvawe08yqg.cloudfront.net/productiongo/s_hero?1620389943","description":"Simple & Readable Syntax: Easier to learn compared to other languages like C++.","price":"250"},{"title":"Go","imageUrl":"https://d2sofvawe08yqg.cloudfront.net/productiongo/s_hero?1620389943","description":"Go lang","price":"35"},{"title":"Go","imageUrl":"https://d2sofvawe08yqg.cloudfront.net/productiongo/s_hero?1620389943","description":"Go is simple lang","price":"36"},{"title":"go","imageUrl":"https://d2sofvawe08yqg.cloudfront.net/productiongo/s_hero?1620389943","description":"Go lang","price":"256","id":"0.3608910292766865"}]